{
"type": "FeatureCollection",
"name": "centroide",
"crs": { "type": "name", "properties": { "name": "urn:ogc:def:crs:OGC:1.3:CRS84" } },
"features": [
{ "type": "Feature", "properties": { "id": 0, "width": 45009.3413, "height": 52710.5767, "area": 2372468336.8101339, "perimeter": 195439.836 }, "geometry": { "type": "Point", "coordinates": [ -46.587408597101607, -23.636276985749848 ] } }
]
}
